bemserver_ui/__init__.py
bemserver_ui/settings.py
bemserver_ui/common/__init__.py
bemserver_ui/common/analysis.py
bemserver_ui/common/const.py
bemserver_ui/common/exceptions.py
bemserver_ui/common/time.py
bemserver_ui/common/tools.py
bemserver_ui/common/tree.py
bemserver_ui/extensions/__init__.py
bemserver_ui/extensions/api_client.py
bemserver_ui/extensions/auth.py
bemserver_ui/extensions/campaign_context.py
bemserver_ui/extensions/error_handlers.py
bemserver_ui/extensions/favicon.py
bemserver_ui/extensions/flask_es6.py
bemserver_ui/extensions/flask_helpers.py
bemserver_ui/extensions/jinja_custom_filters.py
bemserver_ui/extensions/partners.py
bemserver_ui/extensions/plugins.py
bemserver_ui/extensions/timezones/__init__.py
bemserver_ui/extensions/timezones/timezones-areas.json
bemserver_ui/extensions/timezones/timezones-full.json
bemserver_ui/extensions/timezones/timezones-regions.json
bemserver_ui/extensions/timezones/timezones.py
bemserver_ui/internal_api/__init__.py
bemserver_ui/internal_api/campaign_scopes.py
bemserver_ui/internal_api/campaigns.py
bemserver_ui/internal_api/events.py
bemserver_ui/internal_api/notifications.py
bemserver_ui/internal_api/structural_elements.py
bemserver_ui/internal_api/tasks.py
bemserver_ui/internal_api/user_groups.py
bemserver_ui/internal_api/users.py
bemserver_ui/internal_api/analysis/__init__.py
bemserver_ui/internal_api/analysis/completeness.py
bemserver_ui/internal_api/analysis/degree_days.py
bemserver_ui/internal_api/analysis/energy_consumption.py
bemserver_ui/internal_api/analysis/parameters.py
bemserver_ui/internal_api/analysis/weather.py
bemserver_ui/internal_api/semantics/__init__.py
bemserver_ui/internal_api/semantics/weather.py
bemserver_ui/internal_api/semantics/energy/__init__.py
bemserver_ui/internal_api/semantics/energy/consumption.py
bemserver_ui/internal_api/semantics/energy/production.py
bemserver_ui/internal_api/timeseries/__init__.py
bemserver_ui/internal_api/timeseries/data.py
bemserver_ui-0.9.1.dist-info/licenses/LICENSE
bemserver_ui-0.9.1.dist-info/WHEEL
bemserver_ui-0.9.1.dist-info/METADATA
bemserver_ui-0.9.1.dist-info/RECORD
