Metadata-Version: 2.4
Name: bemserver-ui
Version: 0.9.1
Summary: BEMServer web interface
Author-email: Jérôme Lafréchoux <jlafrechoux@nobatek.inef4.com>, David Frédérique <dfrederique@nobatek.inef4.com>
Maintainer-email: Jérôme Lafréchoux <jlafrechoux@nobatek.inef4.com>, David Frédérique <dfrederique@nobatek.inef4.com>
Requires-Python: >=3.9
Classifier: Development Status :: 4 - Beta
Classifier: Intended Audience :: Developers
Classifier: Topic :: Scientific/Engineering
Classifier: License :: OSI Approved :: MIT License
Classifier: Programming Language :: Python :: 3 :: Only
Classifier: Programming Language :: Python :: 3.9
Classifier: Programming Language :: Python :: 3.10
Classifier: Programming Language :: Python :: 3.11
Classifier: Programming Language :: Python :: 3.12
License-File: LICENSE
Requires-Dist: flask>=3.1.0,<4.0.0
Requires-Dist: python-dotenv>=1.0.1,<2.0.0
Requires-Dist: bemserver-api-client>=0.22.0,<0.23.0
Project-URL: Issues, https://github.com/bemserver/bemserver-ui/issues
Project-URL: Source, https://github.com/bemserver/bemserver-ui
